{
  "uuid": "7a1b980d88081e97fbc41e0883736b9e",
  "type": "mlb_card",
  "img": "https://mlb25.theshow.com/rails/active_storage/blobs/redirect/eyJfcmFpbHMiOnsibWVzc2FnZSI6IkJBaHBCQ1h0MFNrPSIsImV4cCI6bnVsbCwicHVyIjoiYmxvYl9pZCJ9fQ==--2e8f57487a647d74b194d90bf14e25ff894d8278/default-mlb-card.webp",
  "baked_img": "https://cards.theshow.com/mlb25/7a1b980d88081e97fbc41e0883736b9e-baked.webp",
  "sc_baked_img": null,
  "name": "Bryan Chi",
  "short_description": null,
  "rarity": "Common",
  "team": "Free Agents",
  "team_short_name": "FA",
  "ovr": 39,
  "series": "Live",
  "series_texture_name": "",
  "series_year": 2017,
  "display_position": "RP",
  "display_secondary_positions": "",
  "jersey_number": "42",
  "age": 25,
  "bat_hand": "R",
  "throw_hand": "R",
  "weight": "205 lbs",
  "height": "6'0\"",
  "born": "Cuba",
  "is_hitter": false,
  "stamina": 33,
  "pitching_clutch": 37,
  "hits_per_bf": 28,
  "k_per_bf": 36,
  "bb_per_bf": 26,
  "hr_per_bf": 44,
  "pitch_velocity": 71,
  "pitch_control": 47,
  "pitch_movement": 60,
  "contact_left": 9,
  "contact_right": 6,
  "power_left": 7,
  "power_right": 5,
  "plate_vision": 5,
  "plate_discipline": 5,
  "batting_clutch": 7,
  "bunting_ability": 34,
  "drag_bunting_ability": 8,
  "hitting_durability": 0,
  "fielding_durability": 72,
  "fielding_ability": 64,
  "arm_strength": 49,
  "arm_accuracy": 58,
  "reaction_time": 56,
  "blocking": 0,
  "speed": 24,
  "baserunning_ability": 7,
  "baserunning_aggression": 3,
  "hit_rank_image": "",
  "fielding_rank_image": "",
  "pitches": [
    {
      "name": "4-Seam Fastball",
      "speed": 92,
      "control": 54,
      "movement": 60
    },
    {
      "name": "Slider",
      "speed": 84,
      "control": 42,
      "movement": 37
    },
    {
      "name": "Curveball",
      "speed": 79,
      "control": 50,
      "movement": 49
    },
    {
      "name": "Cutter",
      "speed": 87,
      "control": 40,
      "movement": 39
    },
    {
      "name": "Sinker",
      "speed": 91,
      "control": 52,
      "movement": 49
    }
  ],
  "quirks": [],
  "is_sellable": true,
  "has_augment": false,
  "augment_text": null,
  "augment_end_date": null,
  "has_matchup": false,
  "stars": null,
  "trend": null,
  "new_rank": 39,
  "has_rank_change": false,
  "event": false,
  "set_name": "CORE",
  "is_live_set": true,
  "ui_anim_index": 0,
  "locations": [
    "COMMUNITY MARKET",
    "DAILY LOGIN REWARD",
    "THE SHOW PACK"
  ]
}